dpss-0.23.3.dist-info/METADATA
dpss-0.23.3.dist-info/WHEEL
dpss-0.23.3.dist-info/licenses/LICENSE
dpss/__init__.py
dpss/dpss.pyd
dpss-0.23.3.dist-info/RECORD
