Metadata-Version: 2.4
Name: dpss
Version: 0.23.3
Requires-Dist: cffi
License-File: LICENSE
Summary: Dynamic-programming subset sum solver with Python bindings
